odoo/addons/l10n_es_aeat_mod303_print/README.rst
odoo/addons/l10n_es_aeat_mod303_print/__init__.py
odoo/addons/l10n_es_aeat_mod303_print/__manifest__.py
odoo/addons/l10n_es_aeat_mod303_print/i18n/es.po
odoo/addons/l10n_es_aeat_mod303_print/report/aeat_mod303.xml
odoo/addons/l10n_es_aeat_mod303_print/report/report_views.xml
odoo/addons/l10n_es_aeat_mod303_print/static/description/icon.png
odoo13_addon_l10n_es_aeat_mod303_print-13.0.1.0.1.dev1.dist-info/METADATA
odoo13_addon_l10n_es_aeat_mod303_print-13.0.1.0.1.dev1.dist-info/WHEEL
odoo13_addon_l10n_es_aeat_mod303_print-13.0.1.0.1.dev1.dist-info/top_level.txt
odoo13_addon_l10n_es_aeat_mod303_print-13.0.1.0.1.dev1.dist-info/RECORD
