Metadata-Version: 2.1
Name: odoo13-addon-l10n_es_aeat_mod303_print
Version: 13.0.1.0.1.dev1
Summary: PDF del model 303
Home-page: https://www.sygel.es
Author: Sygel, Odoo Community Association (OCA)
Author-email: support@odoo-community.org
License: AGPL-3
Classifier: Programming Language :: Python
Classifier: Framework :: Odoo
Classifier: Framework :: Odoo :: 13.0
Classifier: License :: OSI Approved :: GNU Affero General Public License v3
Requires-Python: >=3.5
Requires-Dist: odoo13-addon-l10n-es-aeat-mod303
Requires-Dist: odoo<13.1dev,>=13.0a
